{
  "defaultSeverity": "warning",
  "extends": [
    "tslint:recommended"
  ],
  "linterOptions": {
    "exclude": [
      "node_modules/**"
    ]
  },
  "rules": {
    "quotemark": [true, "single"],
    "indent": [true, "spaces", 2],
    "interface-name": false,
    "ordered-imports": false,
    "object-literal-sort-keys": false,
    "no-consecutive-blank-lines": false,
    "typedef-whitespace": false,
    "max-line-length": false,
    "no-empty": false,
    "member-ordering": false,
    "curly": false,
    "import-spacing": false,
    "no-empty-interface": false
  }
}
